<?xml version="1.0" encoding="utf-8"?>
<ArrayOfLecturer xmlns:xsi="http://www.w3.org/2001/XMLSchema-instance" xmlns:xsd="http://www.w3.org/2001/XMLSchema">
  <Lecturer>
    <ID>10</ID>
    <FirstName>FN10</FirstName>
    <LastName>LN10</LastName>
    <LecturerStatus>SABBATICAL</LecturerStatus>
    <SeniorStuff>true</SeniorStuff>
  </Lecturer>
  <Lecturer>
    <ID>9</ID>
    <FirstName>FN9</FirstName>
    <LastName>LN9</LastName>
    <LecturerStatus>SABBATICAL</LecturerStatus>
    <SeniorStuff>true</SeniorStuff>
  </Lecturer>
  <Lecturer>
    <ID>8</ID>
    <FirstName>FN8</FirstName>
    <LastName>LN8</LastName>
    <LecturerStatus>SABBATICAL</LecturerStatus>
    <SeniorStuff>true</SeniorStuff>
  </Lecturer>
  <Lecturer>
    <ID>7</ID>
    <FirstName>FN7</FirstName>
    <LastName>LN7</LastName>
    <LecturerStatus>SABBATICAL</LecturerStatus>
    <SeniorStuff>true</SeniorStuff>
  </Lecturer>
  <Lecturer>
    <ID>6</ID>
    <FirstName>FN6</FirstName>
    <LastName>LN6</LastName>
    <LecturerStatus>SABBATICAL</LecturerStatus>
    <SeniorStuff>true</SeniorStuff>
  </Lecturer>
  <Lecturer>
    <ID>4</ID>
    <FirstName>FN4</FirstName>
    <LastName>LN4</LastName>
    <LecturerStatus>SABBATICAL</LecturerStatus>
    <SeniorStuff>true</SeniorStuff>
  </Lecturer>
  <Lecturer>
    <ID>2</ID>
    <FirstName>FN2</FirstName>
    <LastName>LN2</LastName>
    <LecturerStatus>SABBATICAL</LecturerStatus>
    <SeniorStuff>true</SeniorStuff>
  </Lecturer>
  <Lecturer>
    <ID>1</ID>
    <FirstName>FN1</FirstName>
    <LastName>LN1</LastName>
    <LecturerStatus>SABBATICAL</LecturerStatus>
    <SeniorStuff>true</SeniorStuff>
  </Lecturer>
  <Lecturer>
    <ID>3</ID>
    <FirstName>FN3</FirstName>
    <LecturerStatus xsi:nil="true" />
    <SeniorStuff>false</SeniorStuff>
  </Lecturer>
</ArrayOfLecturer>